{"name":"thisIsIgnoredTest","id":"com.studentapp.junit.studentinfo.SerenityIDInfo:thisIsIgnoredTest","testCaseName":"com.studentapp.junit.studentinfo.SerenityIDInfo","userStory":{"id":"com.studentapp.junit.studentinfo.SerenityIDInfo","storyName":"Serenity ID info","storyClassName":"com.studentapp.junit.studentinfo.SerenityIDInfo","path":"studentinfo","type":"story"},"featureTag":{"name":"Serenity ID info","type":"story"},"title":"This is ignored test","tags":[{"name":"Studentinfo","type":"feature"},{"name":"Studentinfo/Serenity ID info","type":"story"}],"startTime":"2019-01-07T18:57:17.344+05:30[Asia/Calcutta]","duration":4496,"projectKey":"","annotatedResult":"IGNORED","manual":false,"testSource":"JUnit","result":"IGNORED"}